djangolint/__init__.py
djangolint/compat.py
djangolint/fields.py
djangolint/i18n.py
djangolint/jsons.py
djangolint/meta.py
djangolint/utils.py
djangolint/validators.py
djangolint/locale/wtforms.pot
djangolint/locale/ar/LC_MESSAGES/wtforms.mo
djangolint/locale/ar/LC_MESSAGES/wtforms.po
djangolint/locale/ca/LC_MESSAGES/wtforms.mo
djangolint/locale/ca/LC_MESSAGES/wtforms.po
djangolint/locale/cs_CZ/LC_MESSAGES/wtforms.mo
djangolint/locale/cs_CZ/LC_MESSAGES/wtforms.po
djangolint/locale/cy/LC_MESSAGES/wtforms.mo
djangolint/locale/cy/LC_MESSAGES/wtforms.po
djangolint/locale/de/LC_MESSAGES/wtforms.mo
djangolint/locale/de/LC_MESSAGES/wtforms.po
djangolint/locale/de_CH/LC_MESSAGES/wtforms.mo
djangolint/locale/de_CH/LC_MESSAGES/wtforms.po
djangolint/locale/el/LC_MESSAGES/wtforms.mo
djangolint/locale/el/LC_MESSAGES/wtforms.po
djangolint/locale/en/LC_MESSAGES/wtforms.mo
djangolint/locale/en/LC_MESSAGES/wtforms.po
djangolint/locale/es/LC_MESSAGES/wtforms.mo
djangolint/locale/es/LC_MESSAGES/wtforms.po
djangolint/locale/et/LC_MESSAGES/wtforms.mo
djangolint/locale/et/LC_MESSAGES/wtforms.po
djangolint/locale/fa/LC_MESSAGES/wtforms.mo
djangolint/locale/fa/LC_MESSAGES/wtforms.po
djangolint/locale/fi/LC_MESSAGES/wtforms.po
djangolint/locale/fr/LC_MESSAGES/wtforms.mo
djangolint/locale/fr/LC_MESSAGES/wtforms.po
djangolint/locale/hu/LC_MESSAGES/wtforms.mo
djangolint/locale/hu/LC_MESSAGES/wtforms.po
djangolint/locale/it/LC_MESSAGES/wtforms.mo
djangolint/locale/it/LC_MESSAGES/wtforms.po
djangolint/locale/ja/LC_MESSAGES/wtforms.mo
djangolint/locale/ja/LC_MESSAGES/wtforms.po
djangolint/locale/ko/LC_MESSAGES/wtforms.mo
djangolint/locale/ko/LC_MESSAGES/wtforms.po
djangolint/locale/nb/LC_MESSAGES/wtforms.mo
djangolint/locale/nb/LC_MESSAGES/wtforms.po
djangolint/locale/nl/LC_MESSAGES/wtforms.mo
djangolint/locale/nl/LC_MESSAGES/wtforms.po
djangolint/locale/pl/LC_MESSAGES/wtforms.mo
djangolint/locale/pl/LC_MESSAGES/wtforms.po
djangolint-0.2.1.dist-info/DESCRIPTION.rst
djangolint-0.2.1.dist-info/METADATA
djangolint-0.2.1.dist-info/RECORD
djangolint-0.2.1.dist-info/WHEEL
djangolint-0.2.1.dist-info/metadata.json
djangolint-0.2.1.dist-info/top_level.txt
